<?xml version="1.0" encoding="UTF-8"?>
<tt xmlns="http://www.w3.org/2006/10/ttaf1" xmlns:tts="http://www.w3.org/2006/10/ttaf1#styling" xml:lang="en">
  <head>
    <styling>  </styling>
  </head>
  <body>
    <div xml:lang="en">
      <p begin="00:00:00.00" dur="00:00:01.00">NARRATOR: For the next few minutes, we will look at examples of some of the experiences that can drive the Spiral. After seeing a video example, you will be shown this screen, and asked to select which experience that example illustrates.</p> 
      <p begin="00:00:00.00" dur="00:00:01.00">NARRATOR: Notice what happens to the picture of drug and alcohol-related problems in the center of the screen as you identify the different experiences of the Spiral.</p>
      <p begin="00:00:00.00" dur="00:00:01.00">NARRATOR: Ready to begin? Click Next to play the first example. Then, you'll be asked to identify which component of the Spiral that example represents best.</p>
    </div>
  </body>
</tt>
